setup.py
txriak/__init__.py
txriak/riak.py
txriak/tests.py
txriak.egg-info/PKG-INFO
txriak.egg-info/SOURCES.txt
txriak.egg-info/dependency_links.txt
txriak.egg-info/not-zip-safe
txriak.egg-info/top_level.txt