Metadata-Version: 1.0
Name: txriak
Version: 0.3.2
Summary: txriak is a Twisted module that communicates with the
Home-page: http://bitbucket.org/asi/txriak
Author: Appropriate Solutions, Inc.
Author-email: asi@AppropriateSolutions.com
License: Apache 2.0
Keywords: twisted riak txriak
Platform: Linux
Classifier: Framework :: Twisted
Classifier: Development Status :: 3 - Alpha
